README.md
setup.py
lbrlabs_pulumi_dynatrace/__init__.py
lbrlabs_pulumi_dynatrace/_inputs.py
lbrlabs_pulumi_dynatrace/_utilities.py
lbrlabs_pulumi_dynatrace/activegate_token.py
lbrlabs_pulumi_dynatrace/activegate_updates.py
lbrlabs_pulumi_dynatrace/aix_extension.py
lbrlabs_pulumi_dynatrace/alerting.py
lbrlabs_pulumi_dynatrace/alerting_profile.py
lbrlabs_pulumi_dynatrace/ansible_tower_notification.py
lbrlabs_pulumi_dynatrace/api_detection.py
lbrlabs_pulumi_dynatrace/api_token.py
lbrlabs_pulumi_dynatrace/application_anomalies.py
lbrlabs_pulumi_dynatrace/application_data_privacy.py
lbrlabs_pulumi_dynatrace/application_detection_rule.py
lbrlabs_pulumi_dynatrace/application_detection_rule_v2.py
lbrlabs_pulumi_dynatrace/application_error_rules.py
lbrlabs_pulumi_dynatrace/audit_log.py
lbrlabs_pulumi_dynatrace/autotag.py
lbrlabs_pulumi_dynatrace/autotag_v2.py
lbrlabs_pulumi_dynatrace/aws_anomalies.py
lbrlabs_pulumi_dynatrace/aws_credentials.py
lbrlabs_pulumi_dynatrace/azure_credentials.py
lbrlabs_pulumi_dynatrace/browser_monitor.py
lbrlabs_pulumi_dynatrace/browser_monitor_outage.py
lbrlabs_pulumi_dynatrace/browser_monitor_performance.py
lbrlabs_pulumi_dynatrace/business_events_buckets.py
lbrlabs_pulumi_dynatrace/business_events_metrics.py
lbrlabs_pulumi_dynatrace/business_events_oneagent.py
lbrlabs_pulumi_dynatrace/business_events_processing.py
lbrlabs_pulumi_dynatrace/calculated_service_metric.py
lbrlabs_pulumi_dynatrace/cloud_foundry.py
lbrlabs_pulumi_dynatrace/cloudapp_workloaddetection.py
lbrlabs_pulumi_dynatrace/cloudfoundary_credentials.py
lbrlabs_pulumi_dynatrace/cloudfoundry_credentials.py
lbrlabs_pulumi_dynatrace/connectivity_alerts.py
lbrlabs_pulumi_dynatrace/container_builtin_rule.py
lbrlabs_pulumi_dynatrace/container_rule.py
lbrlabs_pulumi_dynatrace/container_technology.py
lbrlabs_pulumi_dynatrace/credentials.py
lbrlabs_pulumi_dynatrace/custom_anomalies.py
lbrlabs_pulumi_dynatrace/custom_app_anomalies.py
lbrlabs_pulumi_dynatrace/custom_app_crash_rate.py
lbrlabs_pulumi_dynatrace.egg-info/PKG-INFO
lbrlabs_pulumi_dynatrace.egg-info/SOURCES.txt
lbrlabs_pulumi_dynatrace.egg-info/dependency_links.txt
lbrlabs_pulumi_dynatrace.egg-info/not-zip-safe
lbrlabs_pulumi_dynatrace.egg-info/requires.txt
lbrlabs_pulumi_dynatrace.egg-info/top_level.txt
