Metadata-Version: 2.1
Name: lbrlabs-pulumi-dynatrace
Version: 0.1.1a1689433879
Summary: A Pulumi package for creating and managing Dynatrace cloud resources.
Home-page: https://www.pulumi.com
License: Apache-2.0
Project-URL: Repository, https://github.com/lbrlabs/pulumi-dynatrace
Keywords: pulumi dynatrace category/infrastructure lbrlabs
Platform: UNKNOWN
Requires-Python: >=3.7
